Metadata-Version: 1.0
Name: mymathpkg
Version: 0.1
Summary: A math package
Home-page: https://github.com/MarziyaFatema/demo
Author: Marziya
Author-email: shaikhmarzi05@gmail.com
License: UNKNOWN
Platform: UNKNOWN
